rgpubsub/__init__.py
rgpubsub/clients/__init__.py
rgpubsub/clients/google.py
rgpubsub/clients/google_clients.py
rgpubsub/clients/google_rest.py
rgpubsub-0.0.9.dist-info/METADATA
rgpubsub-0.0.9.dist-info/RECORD
rgpubsub-0.0.9.dist-info/WHEEL
rgpubsub-0.0.9.dist-info/top_level.txt
