Metadata-Version: 2.1
Name: rgpubsub
Version: 0.0.9
Summary: Simple helper utility to send Google Pubsub messages easily
Home-page: UNKNOWN
Author: Eirik Tenold
License: UNKNOWN
Platform: UNKNOWN
Classifier: Programming Language :: Python :: 2
Classifier: Programming Language :: Python :: 3
Classifier: Operating System :: OS Independent
Requires-Dist: google-cloud-pubsub
